byecycle-0.1.5.dist-info/METADATA
byecycle-0.1.5.dist-info/WHEEL
byecycle-0.1.5.dist-info/entry_points.txt
byecycle-0.1.5.dist-info/licenses/LICENSE
byecycle/__init__.py
byecycle/__main__.py
byecycle/cli.py
byecycle/draw/__init__.py
byecycle/graph.py
byecycle/misc.py
byecycle/py.typed
byecycle-0.1.5.dist-info/RECORD
