Metadata-Version: 2.1
Name: byecycle
Version: 0.1.5
Summary: Find and expose cyclic imports in python projects.
Author-Email: Arne Caratti <arne.recknagel@hotmail.com>
License: MIT
Classifier: Intended Audience :: Developers
Classifier: License :: OSI Approved :: MIT License
Classifier: Typing :: Typed
Classifier: Programming Language :: Python :: 3.11
Classifier: Operating System :: OS Independent
Requires-Python: >=3.11
Requires-Dist: networkx[default]>=3.1
Requires-Dist: chextra>=0.1.1
Requires-Dist: typer[all]>=0.9.0
Requires-Dist: rich>=13.3
Requires-Dist: matplotlib>=3.7; extra == "draw"
Provides-Extra: draw
